ldap3tool/__init__.py
ldap3tool-0.5.0.dist-info/METADATA
ldap3tool-0.5.0.dist-info/WHEEL
ldap3tool-0.5.0.dist-info/top_level.txt
ldap3tool-0.5.0.dist-info/RECORD
