Metadata-Version: 2.1
Name: ldap3tool
Version: 0.5.0
Summary: Simple wrapper for ldap3
Home-page: https://github.com/lixxu/ldap3tool
Author: Lix Xu
Author-email: xuzenglin@gmail.com
License: BSD
Platform: any
Classifier: Environment :: Web Environment
Classifier: Intended Audience :: Developers
Classifier: License :: OSI Approved :: BSD License
Classifier: Operating System :: OS Independent
Classifier: Programming Language :: Python
Classifier: Topic :: Internet :: WWW/HTTP :: Dynamic Content
Classifier: Topic :: Software Development :: Libraries :: Python Modules
Classifier: Programming Language :: Python :: 2.7
Classifier: Programming Language :: Python :: 3
Requires-Dist: ldap3
